legalmind/__init__.py
legalmind/ai_anhancement.py
legalmind/config.py
legalmind/core.py
legalmind/core_enhanced.py
legalmind/enhanced_search.py
legalmind/prompt_templates.py
legalmind/unified_analysis_engine.py
legalmind/unified_analyzer.py
legalmind/ai/__init__.py
legalmind/ai/legal_ai.py
legalmind/analyzers/__init__.py
legalmind/analyzers/kuhp_2026_analyzer.py
legalmind/api/__init__.py
legalmind/api/analysis_api.py
legalmind/api/server.py
legalmind/providers/__init__.py
legalmind/providers/qodo.py
legalmind/providers/qodo_ai.py
legalmind/providers/fallback/__init__.py
legalmind/providers/fallback/config.py
legalmind/providers/fallback/data_loader.py
legalmind/providers/fallback/enhanced_system.py
legalmind/providers/fallback/system.py
legalmind/providers/fallback/versalaw2_core/__init__.py
legalmind/providers/fallback/versalaw2_core/config.py
legalmind/providers/fallback/versalaw2_core/data_loader.py
legalmind/providers/fallback/versalaw2_core/enhanced_system.py
legalmind/providers/fallback/versalaw2_core/system.py
legalmind_ai-1.1.1.dist-info/METADATA
legalmind_ai-1.1.1.dist-info/WHEEL
legalmind_ai-1.1.1.dist-info/top_level.txt
legalmind_ai-1.1.1.dist-info/RECORD
