Metadata-Version: 2.4
Name: legalmind-ai
Version: 1.1.1
Summary: AI-Powered Legal Assistant for Indonesian Law with KUHP Baru 2026 Support
Author: Your Name
Author-email: Creator Source <creatoropensource@gmail.com>
License: MIT
Project-URL: Homepage, https://github.com/yourusername/legalmind-ai
Project-URL: Documentation, https://github.com/yourusername/legalmind-ai#readme
Project-URL: Repository, https://github.com/yourusername/legalmind-ai
Project-URL: Bug Reports, https://github.com/yourusername/legalmind-ai/issues
Keywords: legal,ai,indonesia,law,kuhp
Classifier: Development Status :: 4 - Beta
Classifier: Intended Audience :: Legal Industry
Classifier: License :: OSI Approved :: MIT License
Classifier: Programming Language :: Python :: 3
Requires-Python: >=3.8
Requires-Dist: openai>=1.0.0
Requires-Dist: requests>=2.25.0
Requires-Dist: python-dotenv>=0.19.0
Dynamic: author
